[{"date": "2018-08-14", "SPI-1": -1.437, "SPI-2": -2.6470000000000002, "SPI-3": -1.663, "SPI-6": -1.611, "SPI-12": -0.459, "SPEI-1": -1.799, "SPEI-2": -2.453, "SPEI-3": -1.7610000000000001, "SPEI-6": -1.548, "SPEI-12": -0.8290000000000001, "VHI": 54.429, "VCI": 74.521, "SMA": -1.913, "CDI": 2.0}, {"date": "2018-08-15", "SPI-1": -1.42, "SPI-2": -2.907, "SPI-3": -1.609, "SPI-6": -1.693, "SPI-12": -0.614, "SPEI-1": -1.8090000000000002, "SPEI-2": -2.455, "SPEI-3": -1.822, "SPEI-6": -1.5630000000000002, "SPEI-12": -0.918, "VHI": 54.429, "VCI": 74.521, "SMA": -1.899, "CDI": 2.0}, {"date": "2018-08-16", "SPI-1": -1.469, "SPI-2": -2.641, "SPI-3": -1.574, "SPI-6": -1.931, "SPI-12": -0.585, "SPEI-1": -2.054, "SPEI-2": -2.454, "SPEI-3": -1.849, "SPEI-6": -1.6, "SPEI-12": -0.93, "VHI": 27.1, "VCI": 46.717, "SMA": -1.998, "CDI": 4.0}, {"date": "2018-08-17", "SPI-1": -1.242, "SPI-2": -2.408, "SPI-3": -1.5550000000000002, "SPI-6": -1.816, "SPI-12": -0.527, "SPEI-1": -1.896, "SPEI-2": -2.268, "SPEI-3": -1.8170000000000002, "SPEI-6": -1.579, "SPEI-12": -0.888, "VHI": 27.1, "VCI": 46.717, "SMA": -2.058, "CDI": 4.0}, {"date": "2018-08-18", "SPI-1": -1.203, "SPI-2": -1.271, "SPI-3": -1.5779999999999998, "SPI-6": -1.7429999999999999, "SPI-12": -0.583, "SPEI-1": -1.764, "SPEI-2": -2.289, "SPEI-3": -1.866, "SPEI-6": -1.593, "SPEI-12": -0.93, "VHI": 27.1, "VCI": 46.717, "SMA": -1.987, "CDI": 4.0}, {"date": "2018-08-19", "SPI-1": -1.323, "SPI-2": -0.657, "SPI-3": -1.712, "SPI-6": -1.763, "SPI-12": -0.63, "SPEI-1": -1.875, "SPEI-2": -2.248, "SPEI-3": -1.859, "SPEI-6": -1.587, "SPEI-12": -0.936, "VHI": 27.1, "VCI": 46.717, "SMA": -1.904, "CDI": 4.0}, {"date": "2018-08-20", "SPI-1": -1.428, "SPI-2": -2.552, "SPI-3": -1.8439999999999999, "SPI-6": -1.755, "SPI-12": -0.541, "SPEI-1": -2.05, "SPEI-2": -2.238, "SPEI-3": -1.983, "SPEI-6": -1.584, "SPEI-12": -0.933, "VHI": 33.972, "VCI": 61.221, "SMA": -1.987, "CDI": 4.0}, {"date": "2018-08-21", "SPI-1": -1.5550000000000002, "SPI-2": -2.378, "SPI-3": -2.241, "SPI-6": -1.741, "SPI-12": -0.6000000000000001, "SPEI-1": -2.042, "SPEI-2": -2.217, "SPEI-3": -2.077, "SPEI-6": -1.596, "SPEI-12": -0.9450000000000001, "VHI": 33.972, "VCI": 61.221, "SMA": -2.094, "CDI": 3.0}, {"date": "2018-08-22", "SPI-1": -1.7149999999999999, "SPI-2": -2.409, "SPI-3": -1.911, "SPI-6": -1.786, "SPI-12": -0.607, "SPEI-1": -2.076, "SPEI-2": -2.2439999999999998, "SPEI-3": -1.978, "SPEI-6": -1.592, "SPEI-12": -0.9510000000000001, "VHI": 33.972, "VCI": 61.221, "SMA": -2.23, "CDI": 3.0}, {"date": "2018-08-23", "SPI-1": -1.77, "SPI-2": -2.779, "SPI-3": -1.877, "SPI-6": -1.752, "SPI-12": -0.61, "SPEI-1": -1.9649999999999999, "SPEI-2": -2.311, "SPEI-3": -1.924, "SPEI-6": -1.603, "SPEI-12": -0.9510000000000001, "VHI": 33.972, "VCI": 61.221, "SMA": -2.242, "CDI": 3.0}, {"date": "2018-08-24", "SPI-1": -1.698, "SPI-2": -2.482, "SPI-3": -1.874, "SPI-6": -1.819, "SPI-12": -0.536, "SPEI-1": -1.799, "SPEI-2": -2.286, "SPEI-3": -1.896, "SPEI-6": -1.62, "SPEI-12": -0.9490000000000001, "VHI": 54.703, "VCI": 70.41, "SMA": -2.246, "CDI": 2.0}]