[{"date": "2018-08-14", "SPI-1": -0.63, "SPI-2": -2.16, "SPI-3": -2.003, "SPI-6": -2.162, "SPI-12": -0.671, "SPEI-1": -1.105, "SPEI-2": -1.8639999999999999, "SPEI-3": -1.8559999999999999, "SPEI-6": -1.8780000000000001, "SPEI-12": -1.23, "VHI": NaN, "VCI": NaN, "SMA": -1.35, "CDI": 5.0}, {"date": "2018-08-15", "SPI-1": -0.61, "SPI-2": -2.204, "SPI-3": -1.845, "SPI-6": -2.124, "SPI-12": -0.7020000000000001, "SPEI-1": -1.123, "SPEI-2": -1.88, "SPEI-3": -1.8980000000000001, "SPEI-6": -1.9180000000000001, "SPEI-12": -1.297, "VHI": NaN, "VCI": NaN, "SMA": -1.351, "CDI": 5.0}, {"date": "2018-08-16", "SPI-1": -0.635, "SPI-2": -2.17, "SPI-3": -2.156, "SPI-6": -2.308, "SPI-12": -0.724, "SPEI-1": -1.138, "SPEI-2": -1.778, "SPEI-3": -1.9180000000000001, "SPEI-6": -1.948, "SPEI-12": -1.323, "VHI": NaN, "VCI": NaN, "SMA": -1.5710000000000002, "CDI": 5.0}, {"date": "2018-08-17", "SPI-1": -0.626, "SPI-2": -2.079, "SPI-3": -2.024, "SPI-6": -2.363, "SPI-12": -0.719, "SPEI-1": -1.071, "SPEI-2": -1.662, "SPEI-3": -1.928, "SPEI-6": -1.955, "SPEI-12": -1.33, "VHI": NaN, "VCI": NaN, "SMA": -1.721, "CDI": 5.0}, {"date": "2018-08-18", "SPI-1": -0.626, "SPI-2": -2.056, "SPI-3": -2.114, "SPI-6": -2.346, "SPI-12": -0.797, "SPEI-1": -1.03, "SPEI-2": -1.67, "SPEI-3": -1.992, "SPEI-6": -1.9929999999999999, "SPEI-12": -1.427, "VHI": NaN, "VCI": NaN, "SMA": -1.891, "CDI": 5.0}, {"date": "2018-08-19", "SPI-1": -0.63, "SPI-2": -2.04, "SPI-3": -2.099, "SPI-6": -2.338, "SPI-12": -0.798, "SPEI-1": -1.096, "SPEI-2": -1.558, "SPEI-3": -1.955, "SPEI-6": -1.99, "SPEI-12": -1.431, "VHI": NaN, "VCI": NaN, "SMA": -2.049, "CDI": 5.0}, {"date": "2018-08-20", "SPI-1": -1.289, "SPI-2": -1.955, "SPI-3": -2.094, "SPI-6": -2.354, "SPI-12": -0.804, "SPEI-1": -1.581, "SPEI-2": -1.592, "SPEI-3": -1.975, "SPEI-6": -1.991, "SPEI-12": -1.423, "VHI": NaN, "VCI": NaN, "SMA": -2.159, "CDI": 2.0}, {"date": "2018-08-21", "SPI-1": -1.5230000000000001, "SPI-2": -1.986, "SPI-3": -2.266, "SPI-6": -2.309, "SPI-12": -0.792, "SPEI-1": -1.713, "SPEI-2": -1.573, "SPEI-3": -2.034, "SPEI-6": -1.9769999999999999, "SPEI-12": -1.437, "VHI": NaN, "VCI": NaN, "SMA": -2.289, "CDI": 2.0}, {"date": "2018-08-22", "SPI-1": -1.583, "SPI-2": -2.023, "SPI-3": -2.424, "SPI-6": -2.359, "SPI-12": -0.778, "SPEI-1": -1.655, "SPEI-2": -1.576, "SPEI-3": -2.053, "SPEI-6": -1.983, "SPEI-12": -1.446, "VHI": NaN, "VCI": NaN, "SMA": -2.297, "CDI": 2.0}, {"date": "2018-08-23", "SPI-1": -1.164, "SPI-2": -1.734, "SPI-3": -2.129, "SPI-6": -2.248, "SPI-12": -0.741, "SPEI-1": -1.505, "SPEI-2": -1.5470000000000002, "SPEI-3": -1.976, "SPEI-6": -1.986, "SPEI-12": -1.399, "VHI": NaN, "VCI": NaN, "SMA": -2.1, "CDI": 2.0}, {"date": "2018-08-24", "SPI-1": -0.993, "SPI-2": -1.695, "SPI-3": -2.103, "SPI-6": -2.284, "SPI-12": -0.723, "SPEI-1": -1.415, "SPEI-2": -1.573, "SPEI-3": -1.9969999999999999, "SPEI-6": -2.007, "SPEI-12": -1.3980000000000001, "VHI": NaN, "VCI": NaN, "SMA": -1.83, "CDI": 2.0}]