[{"date": "2018-08-14", "SPI-1": -1.561, "SPI-2": -2.027, "SPI-3": -1.495, "SPI-6": -2.086, "SPI-12": -1.023, "SPEI-1": -1.613, "SPEI-2": -1.585, "SPEI-3": -1.461, "SPEI-6": -1.826, "SPEI-12": -1.433, "VHI": 56.886, "VCI": 74.679, "SMA": -2.164, "CDI": 2.0}, {"date": "2018-08-15", "SPI-1": -1.775, "SPI-2": -2.113, "SPI-3": -1.756, "SPI-6": -2.136, "SPI-12": -1.038, "SPEI-1": -1.73, "SPEI-2": -1.5859999999999999, "SPEI-3": -1.534, "SPEI-6": -1.861, "SPEI-12": -1.452, "VHI": 56.886, "VCI": 74.679, "SMA": -2.186, "CDI": 2.0}, {"date": "2018-08-16", "SPI-1": -1.8599999999999999, "SPI-2": -2.167, "SPI-3": -1.732, "SPI-6": -2.232, "SPI-12": -1.036, "SPEI-1": -1.7389999999999999, "SPEI-2": -1.612, "SPEI-3": -1.55, "SPEI-6": -1.895, "SPEI-12": -1.475, "VHI": 29.899, "VCI": 58.536, "SMA": -2.286, "CDI": 3.0}, {"date": "2018-08-17", "SPI-1": -1.905, "SPI-2": -2.183, "SPI-3": -1.827, "SPI-6": -2.142, "SPI-12": -1.036, "SPEI-1": -1.812, "SPEI-2": -1.621, "SPEI-3": -1.581, "SPEI-6": -1.912, "SPEI-12": -1.478, "VHI": 29.899, "VCI": 58.536, "SMA": -2.426, "CDI": 3.0}, {"date": "2018-08-18", "SPI-1": -1.822, "SPI-2": -1.766, "SPI-3": -1.831, "SPI-6": -2.218, "SPI-12": -1.205, "SPEI-1": -1.833, "SPEI-2": -1.617, "SPEI-3": -1.592, "SPEI-6": -1.957, "SPEI-12": -1.564, "VHI": 29.899, "VCI": 58.536, "SMA": -2.584, "CDI": 3.0}, {"date": "2018-08-19", "SPI-1": -1.8010000000000002, "SPI-2": -2.176, "SPI-3": -1.8519999999999999, "SPI-6": -2.573, "SPI-12": -1.181, "SPEI-1": -1.888, "SPEI-2": -1.601, "SPEI-3": -1.5779999999999998, "SPEI-6": -1.976, "SPEI-12": -1.5590000000000002, "VHI": 29.899, "VCI": 58.536, "SMA": -2.742, "CDI": 3.0}, {"date": "2018-08-20", "SPI-1": -2.843, "SPI-2": -2.079, "SPI-3": -1.749, "SPI-6": -2.355, "SPI-12": -1.184, "SPEI-1": -2.331, "SPEI-2": -1.584, "SPEI-3": -1.623, "SPEI-6": -2.0, "SPEI-12": -1.574, "VHI": 33.111, "VCI": 63.55, "SMA": -2.862, "CDI": 3.0}, {"date": "2018-08-21", "SPI-1": -3.207, "SPI-2": -2.041, "SPI-3": -1.948, "SPI-6": -2.402, "SPI-12": -1.168, "SPEI-1": -2.32, "SPEI-2": -1.524, "SPEI-3": -1.6640000000000001, "SPEI-6": -1.975, "SPEI-12": -1.577, "VHI": 33.111, "VCI": 63.55, "SMA": -3.026, "CDI": 3.0}, {"date": "2018-08-22", "SPI-1": -3.222, "SPI-2": -1.991, "SPI-3": -2.183, "SPI-6": -2.3, "SPI-12": -1.169, "SPEI-1": -2.205, "SPEI-2": -1.557, "SPEI-3": -1.756, "SPEI-6": -1.9649999999999999, "SPEI-12": -1.587, "VHI": 33.111, "VCI": 63.55, "SMA": -3.19, "CDI": 3.0}, {"date": "2018-08-23", "SPI-1": -2.236, "SPI-2": -1.717, "SPI-3": -1.899, "SPI-6": -2.23, "SPI-12": -1.075, "SPEI-1": -1.88, "SPEI-2": -1.524, "SPEI-3": -1.698, "SPEI-6": -1.932, "SPEI-12": -1.513, "VHI": 33.111, "VCI": 63.55, "SMA": -3.242, "CDI": 3.0}, {"date": "2018-08-24", "SPI-1": -1.335, "SPI-2": -1.31, "SPI-3": -1.579, "SPI-6": -1.968, "SPI-12": -0.852, "SPEI-1": -1.596, "SPEI-2": -1.392, "SPEI-3": -1.541, "SPEI-6": -1.877, "SPEI-12": -1.392, "VHI": 62.696, "VCI": 67.094, "SMA": -2.912, "CDI": 2.0}]