[{"date": "2018-08-14", "SPI-1": -1.689, "SPI-2": -2.8040000000000003, "SPI-3": -1.956, "SPI-6": -1.845, "SPI-12": -0.467, "SPEI-1": -1.846, "SPEI-2": -1.995, "SPEI-3": -1.877, "SPEI-6": -1.831, "SPEI-12": -1.127, "VHI": NaN, "VCI": NaN, "SMA": -2.6630000000000003, "CDI": 2.0}, {"date": "2018-08-15", "SPI-1": -1.8290000000000002, "SPI-2": -2.8609999999999998, "SPI-3": -2.08, "SPI-6": -2.2800000000000002, "SPI-12": -0.452, "SPEI-1": -1.957, "SPEI-2": -2.042, "SPEI-3": -1.921, "SPEI-6": -1.876, "SPEI-12": -1.138, "VHI": NaN, "VCI": NaN, "SMA": -2.632, "CDI": 2.0}, {"date": "2018-08-16", "SPI-1": -1.944, "SPI-2": -2.957, "SPI-3": -2.418, "SPI-6": -2.203, "SPI-12": -0.47700000000000004, "SPEI-1": -2.093, "SPEI-2": -2.211, "SPEI-3": -1.966, "SPEI-6": -1.907, "SPEI-12": -1.172, "VHI": NaN, "VCI": NaN, "SMA": -2.694, "CDI": 2.0}, {"date": "2018-08-17", "SPI-1": -1.9769999999999999, "SPI-2": -2.9450000000000003, "SPI-3": -2.2880000000000003, "SPI-6": -2.2, "SPI-12": -0.489, "SPEI-1": -2.113, "SPEI-2": -2.234, "SPEI-3": -1.992, "SPEI-6": -1.908, "SPEI-12": -1.183, "VHI": NaN, "VCI": NaN, "SMA": -2.782, "CDI": 2.0}, {"date": "2018-08-18", "SPI-1": -1.964, "SPI-2": -2.916, "SPI-3": -2.06, "SPI-6": -2.476, "SPI-12": -0.6880000000000001, "SPEI-1": -2.134, "SPEI-2": -2.266, "SPEI-3": -1.9689999999999999, "SPEI-6": -1.944, "SPEI-12": -1.443, "VHI": NaN, "VCI": NaN, "SMA": -2.868, "CDI": 2.0}, {"date": "2018-08-19", "SPI-1": -1.937, "SPI-2": -2.783, "SPI-3": -1.939, "SPI-6": -2.253, "SPI-12": -0.686, "SPEI-1": -2.125, "SPEI-2": -2.179, "SPEI-3": -1.94, "SPEI-6": -1.951, "SPEI-12": -1.429, "VHI": NaN, "VCI": NaN, "SMA": -2.959, "CDI": 2.0}, {"date": "2018-08-20", "SPI-1": -3.261, "SPI-2": -1.5110000000000001, "SPI-3": -2.442, "SPI-6": -2.432, "SPI-12": -0.6880000000000001, "SPEI-1": -2.457, "SPEI-2": -2.191, "SPEI-3": -1.984, "SPEI-6": -1.966, "SPEI-12": -1.47, "VHI": NaN, "VCI": NaN, "SMA": -3.036, "CDI": 2.0}, {"date": "2018-08-21", "SPI-1": -3.428, "SPI-2": -2.7960000000000003, "SPI-3": -2.51, "SPI-6": -2.372, "SPI-12": -0.718, "SPEI-1": -2.495, "SPEI-2": -2.125, "SPEI-3": -2.045, "SPEI-6": -1.968, "SPEI-12": -1.502, "VHI": NaN, "VCI": NaN, "SMA": -3.093, "CDI": 2.0}, {"date": "2018-08-22", "SPI-1": -3.58, "SPI-2": -2.834, "SPI-3": -2.902, "SPI-6": -2.299, "SPI-12": -0.733, "SPEI-1": -2.333, "SPEI-2": -2.124, "SPEI-3": -2.205, "SPEI-6": -1.9649999999999999, "SPEI-12": -1.524, "VHI": NaN, "VCI": NaN, "SMA": -3.168, "CDI": 2.0}, {"date": "2018-08-23", "SPI-1": -3.116, "SPI-2": -2.675, "SPI-3": -2.509, "SPI-6": -2.247, "SPI-12": -0.6970000000000001, "SPEI-1": -2.257, "SPEI-2": -2.104, "SPEI-3": -2.224, "SPEI-6": -1.9580000000000002, "SPEI-12": -1.488, "VHI": NaN, "VCI": NaN, "SMA": -3.226, "CDI": 2.0}, {"date": "2018-08-24", "SPI-1": -3.048, "SPI-2": -2.694, "SPI-3": -3.16, "SPI-6": -2.219, "SPI-12": -0.669, "SPEI-1": -2.253, "SPEI-2": -2.046, "SPEI-3": -2.245, "SPEI-6": -1.995, "SPEI-12": -1.4969999999999999, "VHI": NaN, "VCI": NaN, "SMA": -3.24, "CDI": 2.0}]