[{"date": "2018-08-14", "SPI-1": -0.906, "SPI-2": -1.044, "SPI-3": -0.927, "SPI-6": -1.193, "SPI-12": 0.122, "SPEI-1": -1.359, "SPEI-2": -1.876, "SPEI-3": -1.542, "SPEI-6": -1.597, "SPEI-12": -0.637, "VHI": NaN, "VCI": NaN, "SMA": -1.767, "CDI": 0.0}, {"date": "2018-08-15", "SPI-1": -0.925, "SPI-2": -2.088, "SPI-3": -1.064, "SPI-6": -1.344, "SPI-12": 0.121, "SPEI-1": -1.369, "SPEI-2": -1.874, "SPEI-3": -1.562, "SPEI-6": -1.63, "SPEI-12": -0.649, "VHI": NaN, "VCI": NaN, "SMA": -1.799, "CDI": 0.0}, {"date": "2018-08-16", "SPI-1": -0.971, "SPI-2": -1.863, "SPI-3": -1.021, "SPI-6": -1.302, "SPI-12": 0.116, "SPEI-1": -1.432, "SPEI-2": -1.9380000000000002, "SPEI-3": -1.568, "SPEI-6": -1.663, "SPEI-12": -0.664, "VHI": NaN, "VCI": NaN, "SMA": -1.875, "CDI": 0.0}, {"date": "2018-08-17", "SPI-1": -0.9490000000000001, "SPI-2": -1.815, "SPI-3": -1.013, "SPI-6": -1.204, "SPI-12": 0.11, "SPEI-1": -1.403, "SPEI-2": -1.884, "SPEI-3": -1.5819999999999999, "SPEI-6": -1.665, "SPEI-12": -0.673, "VHI": NaN, "VCI": NaN, "SMA": -1.927, "CDI": 0.0}, {"date": "2018-08-18", "SPI-1": -0.9470000000000001, "SPI-2": -1.917, "SPI-3": -0.8290000000000001, "SPI-6": -1.139, "SPI-12": -0.101, "SPEI-1": -1.404, "SPEI-2": -1.924, "SPEI-3": -1.516, "SPEI-6": -1.7000000000000002, "SPEI-12": -0.913, "VHI": NaN, "VCI": NaN, "SMA": -2.01, "CDI": 0.0}, {"date": "2018-08-19", "SPI-1": -0.929, "SPI-2": -1.698, "SPI-3": -0.8260000000000001, "SPI-6": -1.155, "SPI-12": -0.1, "SPEI-1": -1.424, "SPEI-2": -1.869, "SPEI-3": -1.479, "SPEI-6": -1.709, "SPEI-12": -0.914, "VHI": NaN, "VCI": NaN, "SMA": -2.096, "CDI": 0.0}, {"date": "2018-08-20", "SPI-1": -2.787, "SPI-2": -1.699, "SPI-3": -0.902, "SPI-6": -1.153, "SPI-12": -0.101, "SPEI-1": -2.279, "SPEI-2": -1.897, "SPEI-3": -1.5, "SPEI-6": -1.7229999999999999, "SPEI-12": -0.916, "VHI": NaN, "VCI": NaN, "SMA": -2.202, "CDI": 2.0}, {"date": "2018-08-21", "SPI-1": -3.018, "SPI-2": -1.724, "SPI-3": -0.9, "SPI-6": -1.202, "SPI-12": -0.11, "SPEI-1": -2.375, "SPEI-2": -1.8820000000000001, "SPEI-3": -1.546, "SPEI-6": -1.729, "SPEI-12": -0.933, "VHI": NaN, "VCI": NaN, "SMA": -2.233, "CDI": 2.0}, {"date": "2018-08-22", "SPI-1": -3.103, "SPI-2": -1.7109999999999999, "SPI-3": -1.337, "SPI-6": -1.2, "SPI-12": -0.11, "SPEI-1": -2.2880000000000003, "SPEI-2": -1.881, "SPEI-3": -1.7930000000000001, "SPEI-6": -1.714, "SPEI-12": -0.9560000000000001, "VHI": NaN, "VCI": NaN, "SMA": -2.309, "CDI": 2.0}, {"date": "2018-08-23", "SPI-1": -2.924, "SPI-2": -1.667, "SPI-3": -1.432, "SPI-6": -1.334, "SPI-12": -0.10200000000000001, "SPEI-1": -2.292, "SPEI-2": -1.8780000000000001, "SPEI-3": -1.8090000000000002, "SPEI-6": -1.724, "SPEI-12": -0.9480000000000001, "VHI": NaN, "VCI": NaN, "SMA": -2.364, "CDI": 2.0}, {"date": "2018-08-24", "SPI-1": -2.835, "SPI-2": -1.686, "SPI-3": -1.353, "SPI-6": -1.231, "SPI-12": -0.096, "SPEI-1": -2.215, "SPEI-2": -1.8479999999999999, "SPEI-3": -1.814, "SPEI-6": -1.725, "SPEI-12": -0.9530000000000001, "VHI": NaN, "VCI": NaN, "SMA": -2.365, "CDI": 2.0}]