[{"date": "2018-08-14", "SPI-1": -0.8240000000000001, "SPI-2": -2.545, "SPI-3": -2.084, "SPI-6": -2.207, "SPI-12": -0.615, "SPEI-1": -1.225, "SPEI-2": -1.921, "SPEI-3": -1.5430000000000001, "SPEI-6": -1.752, "SPEI-12": -1.038, "VHI": 48.826, "VCI": 72.58, "SMA": -1.653, "CDI": 5.0}, {"date": "2018-08-15", "SPI-1": -0.8150000000000001, "SPI-2": -2.676, "SPI-3": -1.911, "SPI-6": -2.296, "SPI-12": -0.728, "SPEI-1": -1.224, "SPEI-2": -1.9689999999999999, "SPEI-3": -1.545, "SPEI-6": -1.791, "SPEI-12": -1.124, "VHI": 48.826, "VCI": 72.58, "SMA": -1.626, "CDI": 5.0}, {"date": "2018-08-16", "SPI-1": -0.861, "SPI-2": -2.713, "SPI-3": -2.01, "SPI-6": -2.295, "SPI-12": -0.763, "SPEI-1": -1.2570000000000001, "SPEI-2": -1.907, "SPEI-3": -1.5939999999999999, "SPEI-6": -1.828, "SPEI-12": -1.147, "VHI": 34.878, "VCI": 48.088, "SMA": -1.798, "CDI": 5.0}, {"date": "2018-08-17", "SPI-1": -0.779, "SPI-2": -2.433, "SPI-3": -2.103, "SPI-6": -2.545, "SPI-12": -0.762, "SPEI-1": -1.185, "SPEI-2": -1.799, "SPEI-3": -1.629, "SPEI-6": -1.826, "SPEI-12": -1.138, "VHI": 34.878, "VCI": 48.088, "SMA": -1.8940000000000001, "CDI": 5.0}, {"date": "2018-08-18", "SPI-1": -0.775, "SPI-2": -2.423, "SPI-3": -2.1, "SPI-6": -2.457, "SPI-12": -0.835, "SPEI-1": -1.153, "SPEI-2": -1.792, "SPEI-3": -1.745, "SPEI-6": -1.8559999999999999, "SPEI-12": -1.189, "VHI": 34.878, "VCI": 48.088, "SMA": -1.9769999999999999, "CDI": 5.0}, {"date": "2018-08-19", "SPI-1": -0.977, "SPI-2": -2.3, "SPI-3": -2.052, "SPI-6": -2.67, "SPI-12": -0.805, "SPEI-1": -1.316, "SPEI-2": -1.686, "SPEI-3": -1.737, "SPEI-6": -1.87, "SPEI-12": -1.195, "VHI": 34.878, "VCI": 48.088, "SMA": -2.046, "CDI": 5.0}, {"date": "2018-08-20", "SPI-1": -1.595, "SPI-2": -2.277, "SPI-3": -2.15, "SPI-6": -2.495, "SPI-12": -0.802, "SPEI-1": -1.703, "SPEI-2": -1.694, "SPEI-3": -1.76, "SPEI-6": -1.874, "SPEI-12": -1.193, "VHI": 34.134, "VCI": 64.625, "SMA": -2.122, "CDI": 3.0}, {"date": "2018-08-21", "SPI-1": -1.778, "SPI-2": -2.257, "SPI-3": -2.305, "SPI-6": -2.607, "SPI-12": -0.8, "SPEI-1": -1.75, "SPEI-2": -1.703, "SPEI-3": -1.812, "SPEI-6": -1.855, "SPEI-12": -1.197, "VHI": 34.134, "VCI": 64.625, "SMA": -2.215, "CDI": 3.0}, {"date": "2018-08-22", "SPI-1": -1.857, "SPI-2": -2.27, "SPI-3": -2.251, "SPI-6": -2.652, "SPI-12": -0.796, "SPEI-1": -1.6960000000000002, "SPEI-2": -1.73, "SPEI-3": -1.823, "SPEI-6": -1.8559999999999999, "SPEI-12": -1.203, "VHI": 34.134, "VCI": 64.625, "SMA": -2.203, "CDI": 3.0}, {"date": "2018-08-23", "SPI-1": -1.375, "SPI-2": -2.054, "SPI-3": -2.322, "SPI-6": -2.249, "SPI-12": -0.723, "SPEI-1": -1.5190000000000001, "SPEI-2": -1.697, "SPEI-3": -1.771, "SPEI-6": -1.861, "SPEI-12": -1.147, "VHI": 34.134, "VCI": 64.625, "SMA": -2.175, "CDI": 3.0}, {"date": "2018-08-24", "SPI-1": -1.184, "SPI-2": -2.078, "SPI-3": -1.834, "SPI-6": -2.534, "SPI-12": -0.704, "SPEI-1": -1.425, "SPEI-2": -1.677, "SPEI-3": -1.784, "SPEI-6": -1.874, "SPEI-12": -1.1219999999999999, "VHI": 49.976, "VCI": 60.981, "SMA": -1.8250000000000002, "CDI": 3.0}]